oarepo_model_builder_relations/__init__.py
oarepo_model_builder_relations/builders.py
oarepo_model_builder_relations/components.py
oarepo_model_builder_relations/datatypes.py
oarepo_model_builder_relations/templates/__init__.py
oarepo_model_builder_relations/templates/record.py.jinja2
tests/__init__.py
tests/conftest.py
tests/referred.yaml
tests/referrer.yaml
tests/test_internal_link.py
tests/test_relation_defaults.py
tests/vocabularies.json
oarepo_model_builder_relations-4.0.11.dist-info/METADATA
oarepo_model_builder_relations-4.0.11.dist-info/WHEEL
oarepo_model_builder_relations-4.0.11.dist-info/entry_points.txt
oarepo_model_builder_relations-4.0.11.dist-info/top_level.txt
oarepo_model_builder_relations-4.0.11.dist-info/RECORD
