Metadata-Version: 2.4
Name: oarepo-model-builder-relations
Version: 4.0.11
Summary: "A model builder plugin to reference relations"
Home-page: https://github.com/oarepo/oarepo-model-builder-relations
Author: Miroslav Simek
Author-email: simek.miroslav@techlib.cz
License: MIT
Keywords: invenio relations model builder
Platform: any
Classifier: Development Status :: 3 - Alpha
Requires-Python: >=3.9
Requires-Dist: oarepo-model-builder>=4.0.0
Requires-Dist: oarepo-model-builder-cf>=4.0.0
Provides-Extra: tests
Requires-Dist: pytest; extra == "tests"
Requires-Dist: black; extra == "tests"
Requires-Dist: autoflake; extra == "tests"
Requires-Dist: isort; extra == "tests"
